clustergrammer2_core/__init__.py
clustergrammer2_core/cli.py
clustergrammer2_core/clustergrammer2_core.py
clustergrammer2_core/clustergrammer_fun/__init__.py
clustergrammer2_core/clustergrammer_fun/calc_clust.py
clustergrammer2_core/clustergrammer_fun/cat_pval.py
clustergrammer2_core/clustergrammer_fun/categories.py
clustergrammer2_core/clustergrammer_fun/data_formats.py
clustergrammer2_core/clustergrammer_fun/downsample_fun.py
clustergrammer2_core/clustergrammer_fun/enrichr_functions.py
clustergrammer2_core/clustergrammer_fun/export_data.py
clustergrammer2_core/clustergrammer_fun/iframe_web_app.py
clustergrammer2_core/clustergrammer_fun/initialize_net.py
clustergrammer2_core/clustergrammer_fun/load_data.py
clustergrammer2_core/clustergrammer_fun/load_vect_post.py
clustergrammer2_core/clustergrammer_fun/make_clust_fun.py
clustergrammer2_core/clustergrammer_fun/make_sim_mat.py
clustergrammer2_core/clustergrammer_fun/make_unique_labels.py
clustergrammer2_core/clustergrammer_fun/make_viz.py
clustergrammer2_core/clustergrammer_fun/normalize_fun.py
clustergrammer2_core/clustergrammer_fun/proc_df_labels.py
clustergrammer2_core/clustergrammer_fun/run_filter.py
clustergrammer2_core-0.3.0.dist-info/AUTHORS.rst
clustergrammer2_core-0.3.0.dist-info/LICENSE
clustergrammer2_core-0.3.0.dist-info/METADATA
clustergrammer2_core-0.3.0.dist-info/WHEEL
clustergrammer2_core-0.3.0.dist-info/entry_points.txt
clustergrammer2_core-0.3.0.dist-info/top_level.txt
clustergrammer2_core-0.3.0.dist-info/RECORD
