Metadata-Version: 2.1
Name: clustergrammer2-core
Version: 0.3.0
Summary: Core functionality for Cthe Clustergrammer2 widget
Home-page: https://github.com/cornhundred/clustergrammer2_core
Author: Nicolas Fernandez
Author-email: nickfloresfernandez@gmail.com
License: MIT license
Keywords: clustergrammer2_core
Platform: UNKNOWN
Classifier: Development Status :: 2 - Pre-Alpha
Classifier: Intended Audience :: Developers
Classifier: License :: OSI Approved :: MIT License
Classifier: Natural Language :: English
Classifier: Programming Language :: Python :: 3
Classifier: Programming Language :: Python :: 3.6
Classifier: Programming Language :: Python :: 3.7
Classifier: Programming Language :: Python :: 3.8
Requires-Python: >=3.6
Requires-Dist: Click (>=7.0)
